focmech3d/__init__.py
focmech3d/datautils.py
focmech3d/focal_mechanism.py
focmech3d/mpl_plots.py
focmech3d/plotcoords.py
focmech3d/topoprofile.py
focmech3d/vector_math.py
focmech3d-0.0.1.dist-info/LICENSE
focmech3d-0.0.1.dist-info/METADATA
focmech3d-0.0.1.dist-info/WHEEL
focmech3d-0.0.1.dist-info/top_level.txt
focmech3d-0.0.1.dist-info/RECORD
