Metadata-Version: 2.1
Name: focmech3d
Version: 0.0.1
Summary: Package for displaying 3D focal mechanisms
Home-page: https://github.com/JuanS-OSORNOB/3DFocal_Mechanism
Author: Juan Sebastián Osorno Bolívar & Amy Teegarden
Author-email: focmech3d@gmail.com
License: UNKNOWN
Platform: UNKNOWN
Classifier: Programming Language :: Python :: 3
Classifier: License :: OSI Approved :: MIT License
Classifier: Development Status :: 3 - Alpha
Classifier: Intended Audience :: Science/Research
Classifier: Intended Audience :: Education
Classifier: Topic :: Scientific/Engineering
Classifier: Framework :: Matplotlib
Requires-Python: >=3.6
